devToolsSPFC/MLibrary.py
devToolsSPFC/__init__.py
devToolsSPFC-0.0.1.dist-info/METADATA
devToolsSPFC-0.0.1.dist-info/WHEEL
devToolsSPFC-0.0.1.dist-info/license
devToolsSPFC-0.0.1.dist-info/top_level.txt
devToolsSPFC-0.0.1.dist-info/RECORD
