Metadata-Version: 2.1
Name: devToolsSPFC
Version: 0.0.1
Summary: devToolsSPFC
Home-page: UNKNOWN
Author: Dev Raj
Author-email: dev.raj.pandey.7836@gmail.com
License: UNKNOWN
Keywords: python,easy-to-use,one line code,simple,Dev Raj
Platform: UNKNOWN
Classifier: Development Status :: 1 - Planning
Classifier: Intended Audience :: Developers
Classifier: Programming Language :: Python :: 3
Classifier: Operating System :: Unix
Classifier: Operating System :: MacOS :: MacOS X
Classifier: Operating System :: Microsoft :: Windows
License-File: license
Requires-Dist: pyautogui
Requires-Dist: randfacts
Requires-Dist: keyboard
